{"IL5GrE9edCKrNzDpsiG6Kw==":"gaming4life.%20ejer%20disse%20billeder%20(1)-40x14.png","eoAnCMz0KUeKsxXhWm24fg==":"gaming4life.%20ejer%20disse%20billeder%20(1)-348x124.png","h1vxjLjcD0YT5hcAzinH9A==":"gaming4life.%20ejer%20disse%20billeder%20(37)-2000x1250.jpg","cQgx1mcxQ0eyBMOP5jxTSg==":"gaming4life.%20ejer%20disse%20billeder%20(53)-866x486.jpg","EHs23bhXjsEoiRzdDhfdGQ==":"06.jpg","sT80Y4RCGNBrSInGgrjIuA==":"background3.jpg","mS4cUYwSDiiUY+5fr7KwUQ==":"gaming4life.%20ejer%20disse%20billeder%20(10)-187x181.png","XT85hOl8Y3TKDh2U0op/nQ==":"gaming4life.%20ejer%20disse%20billeder%20(5)-206x212.png","3mOkAWu6CN0A9tpN/Dk2TQ==":"gaming4life.%20ejer%20disse%20billeder%20(6)-178x164.png","bw43p1Dz2wY9KMis3ZYs7g==":"gaming4life.%20ejer%20disse%20billeder%20(8)-161x172.png","CjiNCiiJfyyjhuKZ0lsNNw==":"gaming4life.%20ejer%20disse%20billeder%20(9)-219x216.png","8CV8NOcq4ZJeRUlIa4IxXw==":"gaming4life.%20ejer%20disse%20billeder%20(7)-156x187.png","hp2Yv3+WBokx6uD0r/wtXg==":"gaming4life.%20ejer%20disse%20billeder%20(27)-2000x1000.jpg","qKmWbzI8go+PHnVnQvnUeQ==":"white-background-images-8-1162x1162.jpg","PJwdt9el+iFq58FZqhBZYw==":"white-background-images-8-1298x1298.jpg","WJ2fDPg6Xwx7Ebf+rzR2Sg==":"gaming4life.-ejer-disse-billeder-7-240x286.jpg","pNBbVNLP5cJZO0iU+df8uw==":"5-infinite-white-studio-backdrops-1920x389.jpg","+7xJObE4XhISNw5iN3ALvA==":"4564645645645645-1343x387.jpg","tAl1qEItzbFhcYStkubtOw==":"screen_capture%202019-12-22_12-09-1_am-75x82.png","ier3nMx5YKymJi0TZy/a/g==":"screen_capture%202019-12-22_12-10-37_am-161x185.png","xMmDwT88G5yA60sKxlIbeg==":"screen_capture%202019-12-22_12-19-10_am-201x199.png","lndtYkZJ15c2A7nanWNQTA==":"screen_capture%202019-12-22_12-17-29_am-200x190.png","zw96D0kCivOxbrcG7SdH5A==":"screen_capture%202019-12-22_12-16-38_am-200x183.png"}